spark_ai/__init__.py
spark_ai/spark.py
spark_ai/dbs/__init__.py
spark_ai/dbs/opensearch.py
spark_ai/dbs/pinecone.py
spark_ai/endpoints/__init__.py
spark_ai/endpoints/sagemaker.py
spark_ai/files/__init__.py
spark_ai/files/docx.py
spark_ai/files/pdf.py
spark_ai/files/text.py
spark_ai/llms/__init__.py
spark_ai/llms/bedrock.py
spark_ai/llms/openai.py
spark_ai/llms/sagemaker.py
spark_ai/webapps/__init__.py
spark_ai/webapps/slack.py
prophecy_spark_ai-0.1.14.dist-info/METADATA
prophecy_spark_ai-0.1.14.dist-info/WHEEL
prophecy_spark_ai-0.1.14.dist-info/top_level.txt
prophecy_spark_ai-0.1.14.dist-info/RECORD
