Metadata-Version: 2.1
Name: prophecy-spark-ai
Version: 0.1.14
Summary: High-performance AI/ML library for Spark to build and deploy your LLM applications in production.
Home-page: https://github.com/prophecy-io/spark-ai
Keywords: python,prophecy
Requires-Dist: slack-sdk>=3.21.3
Requires-Dist: openai[datalib]>=0.27.8
Requires-Dist: pinecone>=6.0.0
Requires-Dist: python-dotenv>=1.0.0
Requires-Dist: requests>=2.31.0
Requires-Dist: beautifulsoup4>=4.12.2
Requires-Dist: unstructured[all-docs]>=0.16.14
Requires-Dist: numpy>=1.24.3
Requires-Dist: boto3>=1.28.62
Requires-Dist: opensearch-py>=2.6.0
Requires-Dist: pdf2image>=1.17.0
